{
    "modules": [
        {
            "config": {
                "position": [
                    43,
                    133
                ]
            },
            "name": "New Model Object",
            "value": {
                "actionGroup": {
                    "_default0_list": true,
                    "_default1_show": true,
                    "_default2_new_create": true,
                    "_default3_edit_update": true,
                    "_default4_delete": true,
                    "customActions": []
                },
                "name": "Turnier",
                "objectsettings": {
                    "addDeletedField": true,
                    "addHiddenField": true,
                    "addStarttimeEndtimeFields": true,
                    "aggregateRoot": true,
                    "categorizable": false,
                    "description": "",
                    "mapToTable": "",
                    "parentClass": "",
                    "sorting": false,
                    "type": "Entity",
                    "uid": "951285923975"
                },
                "propertyGroup": {
                    "properties": [
                        {
                            "allowedFileTypes": "",
                            "maxItems": "1",
                            "propertyDescription": "titel of the turnier",
                            "propertyIsExcludeField": false,
                            "propertyIsRequired": true,
                            "propertyName": "titel",
                            "propertyType": "String",
                            "uid": "196082701233"
                        },
                        {
                            "allowedFileTypes": "",
                            "maxItems": "1",
                            "propertyDescription": "location of the turnier",
                            "propertyIsExcludeField": false,
                            "propertyIsRequired": true,
                            "propertyName": "location",
                            "propertyType": "String",
                            "uid": "1049684644022"
                        },
                        {
                            "allowedFileTypes": "",
                            "maxItems": "1",
                            "propertyDescription": "date of the turnier",
                            "propertyIsExcludeField": false,
                            "propertyIsRequired": true,
                            "propertyName": "dateturnier",
                            "propertyType": "NativeDate",
                            "uid": "13382040635"
                        }
                    ]
                },
                "relationGroup": {
                    "relations": [
                        {
                            "foreignRelationClass": "",
                            "lazyLoading": false,
                            "propertyIsExcludeField": true,
                            "relationDescription": "",
                            "relationName": "spieler",
                            "relationType": "zeroToOne",
                            "relationWire": "[wired]",
                            "uid": "1204117684914"
                        }
                    ]
                }
            }
        },
        {
            "config": {
                "position": [
                    409,
                    132
                ]
            },
            "name": "New Model Object",
            "value": {
                "actionGroup": {
                    "_default0_list": true,
                    "_default1_show": true,
                    "_default2_new_create": true,
                    "_default3_edit_update": true,
                    "_default4_delete": true,
                    "customActions": []
                },
                "name": "Spieler",
                "objectsettings": {
                    "addDeletedField": true,
                    "addHiddenField": true,
                    "addStarttimeEndtimeFields": true,
                    "aggregateRoot": true,
                    "categorizable": false,
                    "description": "",
                    "mapToTable": "",
                    "parentClass": "",
                    "sorting": false,
                    "type": "Entity",
                    "uid": "1087266904515"
                },
                "propertyGroup": {
                    "properties": [
                        {
                            "allowedFileTypes": "",
                            "maxItems": "1",
                            "propertyDescription": "name of the player",
                            "propertyIsExcludeField": false,
                            "propertyIsRequired": true,
                            "propertyName": "name",
                            "propertyType": "String",
                            "uid": "266301743971"
                        },
                        {
                            "allowedFileTypes": "",
                            "maxItems": "1",
                            "propertyDescription": "",
                            "propertyIsExcludeField": false,
                            "propertyIsRequired": true,
                            "propertyName": "strength",
                            "propertyType": "Integer",
                            "uid": "505964874740"
                        }
                    ]
                },
                "relationGroup": {
                    "relations": [
                        {
                            "foreignRelationClass": "",
                            "lazyLoading": false,
                            "propertyIsExcludeField": true,
                            "relationDescription": "",
                            "relationName": "spielmodus",
                            "relationType": "zeroToOne",
                            "relationWire": "[wired]",
                            "uid": "708080480184"
                        }
                    ]
                }
            }
        },
        {
            "config": {
                "position": [
                    700,
                    138
                ]
            },
            "name": "New Model Object",
            "value": {
                "actionGroup": {
                    "_default0_list": true,
                    "_default1_show": true,
                    "_default2_new_create": true,
                    "_default3_edit_update": true,
                    "_default4_delete": true,
                    "customActions": []
                },
                "name": "Spielmodus",
                "objectsettings": {
                    "addDeletedField": true,
                    "addHiddenField": true,
                    "addStarttimeEndtimeFields": true,
                    "aggregateRoot": false,
                    "categorizable": false,
                    "description": "",
                    "mapToTable": "",
                    "parentClass": "",
                    "sorting": false,
                    "type": "ValueObject",
                    "uid": "454370135277"
                },
                "propertyGroup": {
                    "properties": [
                        {
                            "allowedFileTypes": "",
                            "maxItems": "1",
                            "propertyDescription": "",
                            "propertyIsExcludeField": false,
                            "propertyIsRequired": false,
                            "propertyName": "single",
                            "propertyType": "Boolean",
                            "uid": "410589114071"
                        },
                        {
                            "allowedFileTypes": "",
                            "maxItems": "1",
                            "propertyDescription": "",
                            "propertyIsExcludeField": false,
                            "propertyIsRequired": false,
                            "propertyName": "doppel",
                            "propertyType": "Boolean",
                            "uid": "607937538500"
                        },
                        {
                            "allowedFileTypes": "",
                            "maxItems": "1",
                            "propertyDescription": "",
                            "propertyIsExcludeField": false,
                            "propertyIsRequired": false,
                            "propertyName": "mixed",
                            "propertyType": "Boolean",
                            "uid": "460779036595"
                        }
                    ]
                },
                "relationGroup": {
                    "relations": []
                }
            }
        }
    ],
    "properties": {
        "backendModules": [],
        "description": "Turnier mit Spielerverwaltung",
        "emConf": {
            "category": "plugin",
            "custom_category": "",
            "dependsOn": "typo3 => 6.2\n",
            "disableLocalization": false,
            "disableVersioning": false,
            "sourceLanguage": "en",
            "state": "alpha",
            "targetVersion": "6.2",
            "version": ""
        },
        "extensionKey": "turnierverwaltung",
        "name": "Turnierverwaltung",
        "originalExtensionKey": "",
        "persons": [],
        "plugins": [],
        "vendorName": "Vaupel"
    },
    "wires": [
        {
            "src": {
                "moduleId": 0,
                "terminal": "relationWire_0",
                "uid": "1204117684914"
            },
            "tgt": {
                "moduleId": 1,
                "terminal": "SOURCES",
                "uid": "1087266904515"
            }
        },
        {
            "src": {
                "moduleId": 1,
                "terminal": "relationWire_0",
                "uid": "708080480184"
            },
            "tgt": {
                "moduleId": 2,
                "terminal": "SOURCES",
                "uid": "454370135277"
            }
        }
    ],
    "log": {
        "last_modified": "2014-10-23 02:35",
        "extension_builder_version": "6.2.0",
        "be_user": " (1)"
    }
}